fugit-0.3.3.dist-info/METADATA
fugit-0.3.3.dist-info/WHEEL
fugit-0.3.3.dist-info/entry_points.txt
fugit-0.3.3.dist-info/licenses/LICENSE.txt
fugit/__init__.py
fugit/cli/__init__.py
fugit/cli/run.py
fugit/core/__init__.py
fugit/core/console.py
fugit/core/diffing/__init__.py
fugit/core/diffing/gitpython/__init__.py
fugit/core/diffing/gitpython/operations.py
fugit/core/diffing/gitpython/structures.py
fugit/core/diffing/logic.py
fugit/core/diffing/pygit2/__init__.py
fugit/core/diffing/pygit2/operations.py
fugit/core/diffing/pygit2/structures.py
fugit/core/error_handlers.py
fugit/core/errors.py
fugit/core/io.py
fugit/core/parsing/__init__.py
fugit/core/parsing/file_diff.py
fugit/core/parsing/optional_specifier.py
fugit/core/pipes.py
fugit/interfaces/__init__.py
fugit/interfaces/debug.py
fugit/interfaces/diffing.py
fugit/interfaces/display.py
fugit/py.typed
fugit/types/__init__.py
fugit/types/signed_int.py
fugit-0.3.3.dist-info/RECORD
