Metadata-Version: 2.1
Name: fugit
Version: 0.3.3
Summary: Git diff handling in Python.
Keywords: git pydantic pypi
Author-Email: Louis Maddox <louismmx@gmail.com>
License: MIT
Classifier: Development Status :: 3 - Alpha
Classifier: Framework :: Pydantic :: 2
Classifier: Framework :: Pydantic
Classifier: Intended Audience :: Developers
Classifier: License :: OSI Approved :: MIT License
Classifier: Programming Language :: Python :: 3.10
Classifier: Programming Language :: Python :: 3.11
Classifier: Programming Language :: Python
Classifier: Topic :: Software Development :: Libraries
Project-URL: Homepage, https://github.com/lmmx/fugit
Project-URL: Repository, https://github.com/lmmx/fugit.git
Requires-Python: <3.12,>=3.10
Requires-Dist: GitPython>=3.1.40
Requires-Dist: defopt
Requires-Dist: parse-type>=0.6.2
Requires-Dist: parse>=1.20.0
Requires-Dist: pydantic>=2.4.2
Requires-Dist: pygit2>=1.13.3
Requires-Dist: rich>=13.7.0
